<corpus>
<text title="# I:331">
<paragraph n="1">
<sentence n="1" id="59b6d3a-59b58f7">
<w >I</w>
<w >:</w>
<w >331</w>
<w >Här</w>
<w >äpter</w>
<w >star</w>
<w >sancte</w>
<w >felicule</w>
<w >hälga</w>
<w >liffwerne</w>
<w >oc</w>
<w >sancte</w>
<w >petronille</w>
<w >.</w>
</sentence>
</paragraph>
<paragraph n="2">
<sentence n="2" id="59b58f7-59b53dc">
<w >Sancte</w>
<w >pädhar</w>
<w >appostolus</w>
<w >haffde</w>
<w >ena</w>
<w >hälogha</w>
<w >dotter</w>
<w >hennas</w>
<w >nampn</w>
<w >war</w>
<w >petronilla</w>
<w >,</w>
<w >oc</w>
<w >äpther</w>
<w >sancti</w>
<w >petri</w>
<w >wilia</w>
<w >war</w>
<w >hon</w>
<w >paralitica</w>
<w >,</w>
<w >thz</w>
<w >är</w>
<w >nwmmen</w>
<w >ällar</w>
<w >halffuir</w>
<w >horttakin</w>
<w >,</w>
<w >i</w>
<w >hännas</w>
<w >hws</w>
<w >plägadhe</w>
<w >sancte</w>
<w >pädhars</w>
<w >kännesena</w>
<w >samnas</w>
<w >,</w>
<w >oc</w>
<w >faa</w>
<w >sik</w>
<w >ther</w>
<w >ätha</w>
<w >oc</w>
<w >drikka</w>
<w >,</w>
<w >Thz</w>
<w >händhe</w>
<w >at</w>
<w >en</w>
<w >aff</w>
<w >känneswenomen</w>
<w >,</w>
<w >som</w>
<w >kalladhes</w>
<w >tytus</w>
<w >,</w>
<w >sagdhe</w>
<w >til</w>
<w >sancte</w>
<w >pädhar</w>
<w >,</w>
<w >alt</w>
<w >krankt</w>
<w >folk</w>
<w >som</w>
<w >tik</w>
<w >komber</w>
<w >,</w>
<w >faa</w>
<w >sina</w>
<w >helso</w>
<w >,</w>
<w >hwi</w>
<w >tilstädher</w>
<w >thu</w>
<w >at</w>
<w >petronilla</w>
<w >ligger</w>
<w >krank</w>
<w >Appostolen</w>
<w >swaradhe</w>
<w >,</w>
<w >hänne</w>
<w >tarffuas</w>
<w >bäther</w>
<w >wara</w>
<w >krank</w>
<w >än</w>
<w >helbrigdha</w>
<w >,</w>
<w >än</w>
<w >oppa</w>
<w >thz</w>
<w >at</w>
<w >ey</w>
<w >nakrom</w>
<w >skuli</w>
<w >synas</w>
<w >omöghelikit</w>
<w >,</w>
<w >at</w>
<w >hon</w>
<w >aff</w>
<w >minom</w>
<w >ordhom</w>
<w >maghe</w>
<w >helbrigdha</w>
<w >wardha</w>
<w >,</w>
<w >Tha</w>
<w >sigher</w>
<w >iak</w>
<w >tik</w>
<w >petronilla</w>
<w >,</w>
<w >i</w>
<w >ihesu</w>
<w >cristi</w>
<w >nampn</w>
<w >stat</w>
<w >opp</w>
<w >oc</w>
<w >thiäna</w>
<w >os</w>
<w >,</w>
<w >oc</w>
<w >iämsköt</w>
<w >stodh</w>
<w >hon</w>
<w >opp</w>
<w >,</w>
<w >helbrigdha</w>
<w >,</w>
<w >oc</w>
<w >tiänte</w>
<w >them</w>
<w >,</w>
<w >Oc</w>
<w >nar</w>
<w >ämbetet</w>
<w >ällar</w>
<w >tiänisten</w>
<w >war</w>
<w >fulkompnat</w>
<w >,</w>
<w >bödh</w>
<w >sancte</w>
<w >pädhar</w>
<w >hänne</w>
<w >gaa</w>
<w >til</w>
<w >sywka</w>
<w >sänghena</w>
<w >igän</w>
<w >,</w>
<w >Oc</w>
<w >nar</w>
<w >sancta</w>
<w >petronilla</w>
<w >war</w>
<w >fulbordhat</w>
<w >i</w>
<w >gudz</w>
<w >räddogho</w>
<w >,</w>
<w >tha</w>
<w >wart</w>
<w >ey</w>
<w >at</w>
<w >enast</w>
<w >hon</w>
<w >siälff</w>
<w >helbrigdha</w>
<w >,</w>
<w >wtan</w>
<w >iämwäl</w>
<w >manghe</w>
<w >andre</w>
<w >för</w>
</sentence>
</paragraph>
<paragraph n="3">
<sentence n="3" id="59b53dc-59beee0">
<w >I</w>
<w >:</w>
<w >332</w>
<w >hännas</w>
<w >gudelika</w>
<w >bön</w>
<w >,</w>
<w >skult</w>
<w >,</w>
<w >fingho</w>
<w >sina</w>
<w >helso</w>
<w >igän</w>
<w >,</w>
<w >aff</w>
<w >margskona</w>
<w >krankdomom</w>
<w >,</w>
<w >än</w>
<w >förtänskul</w>
<w >at</w>
<w >petronilla</w>
<w >war</w>
<w >ganzska</w>
<w >mykyt</w>
<w >faghor</w>
<w >oc</w>
<w >wän</w>
<w >,</w>
<w >tha</w>
<w >kom</w>
<w >til</w>
<w >hänna</w>
<w >en</w>
<w >mäktogher</w>
<w >grewe</w>
<w >,</w>
<w >myndogher</w>
<w >oc</w>
<w >karsker</w>
<w >man</w>
<w >,</w>
<w >haffuandhes</w>
<w >mz</w>
<w >sik</w>
<w >sith</w>
<w >riddarskap</w>
<w >,</w>
<w >menandhes</w>
<w >hänne</w>
<w >strax</w>
<w >bortföra</w>
<w >,</w>
<w >oc</w>
<w >haffua</w>
<w >hänne</w>
<w >sik</w>
<w >til</w>
<w >hustru</w>
<w >,</w>
<w >Thänne</w>
<w >mäktoghe</w>
<w >greffwen</w>
<w >heth</w>
<w >flacchus</w>
<w >oc</w>
<w >taladhe</w>
<w >han</w>
<w >mykyt</w>
<w >myndhelika</w>
<w >om</w>
<w >sith</w>
<w >ärandhe</w>
<w >til</w>
<w >sanctam</w>
<w >petronillam</w>
<w >¶</w>
<w >Nar</w>
<w >iomffrun</w>
<w >hört</w>
<w >haffde</w>
<w >greffwans</w>
<w >ordh</w>
<w >,</w>
<w >swaradhe</w>
<w >hon</w>
<w >säfflika</w>
<w >sighiandis</w>
<w >,</w>
<w >hedherlike</w>
<w >herra</w>
<w >,</w>
<w >i</w>
<w >kommen</w>
<w >här</w>
<w >til</w>
<w >mik</w>
<w >ena</w>
<w >blotta</w>
<w >pigho</w>
<w >mz</w>
<w >manghom</w>
<w >wänktom</w>
<w >riddarom</w>
<w >,</w>
<w >än</w>
<w >är</w>
<w >thz</w>
<w >idart</w>
<w >alffwara</w>
<w >,</w>
<w >at</w>
<w >i</w>
<w >wilin</w>
<w >mik</w>
<w >til</w>
<w >idhra</w>
<w >hustru</w>
<w >haffwa</w>
<w >,</w>
<w >tha</w>
<w >kommen</w>
<w >igän</w>
<w >äpther</w>
<w >iij</w>
<w >dagha</w>
<w >,</w>
<w >haffuandhes</w>
<w >mz</w>
<w >idher</w>
<w >höffwiska</w>
<w >iomffrur</w>
<w >,</w>
<w >oc</w>
<w >flere</w>
<w >hedherlika</w>
<w >dandhe</w>
<w >qwinnor</w>
<w >,</w>
<w >at</w>
<w >iak</w>
<w >mz</w>
<w >them</w>
<w >matte</w>
<w >hedherlika</w>
<w >komma</w>
<w >til</w>
<w >idhart</w>
<w >palacium</w>
<w >,</w>
<w >widh</w>
<w >saadana</w>
<w >ordh</w>
<w >gaff</w>
<w >greffwen</w>
<w >sik</w>
<w >allaledhis</w>
<w >wäl</w>
<w >tilfridz</w>
<w >,</w>
<w >Oc</w>
<w >i</w>
<w >tässom</w>
<w >förelagdhom</w>
<w >thima</w>
<w >som</w>
<w >war</w>
<w >tre</w>
<w >dagha</w>
<w >,</w>
<w >bleff</w>
<w >hälgha</w>
<w >iomffrun</w>
<w >stadhelika</w>
<w >i</w>
<w >gudhelikom</w>
<w >bönom</w>
<w >fasto</w>
<w >,</w>
<w >oc</w>
<w >waku</w>
<w >,</w>
<w >oc</w>
<w >miskundhsamlikom</w>
<w >gärniggom</w>
<w >bidhiandes</w>
<w >gudh</w>
<w >jnnerlika</w>
<w >at</w>
<w >hon</w>
<w >matte</w>
<w >komma</w>
<w >til</w>
<w >honom</w>
<w >,</w>
<w >som</w>
<w >är</w>
<w >iomffrunna</w>
<w >son</w>
<w >,</w>
<w >mz</w>
<w >iomffrulikom</w>
<w >renlek</w>
<w >,</w>
<w >ok</w>
<w >aldrigh</w>
<w >tilbwndhin</w>
<w >wardha</w>
<w >them</w>
<w >hedhniska</w>
<w >greffwanom</w>
<w >¶</w>
<w >Äpther</w>
<w >farandes</w>
<w >mz</w>
<w >storom</w>
<w >skara</w>
<w >aff</w>
<w >prydhelikom</w>
<w >iomfrum</w>
<w >,</w>
<w >mz</w>
<w >mäktoghom</w>
<w >frughom</w>
<w >,</w>
<w >Oc</w>
<w >om</w>
<w >samma</w>
<w >daghen</w>
<w >,</w>
<w >war</w>
<w >til</w>
<w >hälga</w>
<w >iomffrwnna</w>
<w >kommen</w>
<w >sanctus</w>
<w >nichomedus</w>
<w >prester</w>
<w >,</w>
<w >oc</w>
<w >haffde</w>
<w >han</w>
<w >högtidhelika</w>
<w >mässo</w>
<w >,</w>
<w >för</w>
<w >sancta</w>
<w >petronille</w>
<w >,</w>
<w >oc</w>
<w >nar</w>
<w >mässan</w>
<w >war</w>
<w >ändat</w>
<w >,</w>
<w >oc</w>
<w >wälsignilsen</w>
<w >giffwin</w>
<w >,</w>
<w >oc</w>
<w >hälga</w>
<w >iomffrun</w>
<w >haffde</w>
<w >mz</w>
<w >höxsta</w>
<w >gudelikhet</w>
<w >anamat</w>
<w >wärdogasta</w>
<w >ihesu</w>
<w >cristi</w>
<w >likama</w>
<w >,</w>
</sentence>
</paragraph>
<paragraph n="4">
<sentence n="4" id="59beee0-59b797a">
<w >I</w>
<w >:</w>
<w >333</w>
<w >nidherbögdhe</w>
<w >hon</w>
<w >huffwodhit</w>
<w >wndher</w>
<w >klädhen</w>
<w >i</w>
<w >sänghenne</w>
<w >,</w>
<w >oc</w>
<w >opgaff</w>
<w >gudhi</w>
<w >sina</w>
<w >siäl</w>
<w >,</w>
<w >Oc</w>
<w >wart</w>
<w >tha</w>
<w >swa</w>
<w >giort</w>
<w >,</w>
<w >at</w>
<w >thän</w>
<w >iomffruskaren</w>
<w >,</w>
<w >oc</w>
<w >mäktogha</w>
<w >frughor</w>
<w >som</w>
<w >komna</w>
<w >waro</w>
<w >at</w>
<w >fölya</w>
<w >sancte</w>
<w >petronille</w>
<w >til</w>
<w >högtidheliket</w>
<w >brylloppe</w>
<w >,</w>
<w >the</w>
<w >wordho</w>
<w >tha</w>
<w >hänne</w>
<w >äptherföliandes</w>
<w >til</w>
<w >graffwena</w>
<w >¶</w>
<w >Sidhan</w>
<w >mäktoghe</w>
<w >herran</w>
<w >greffwe</w>
<w >flacchus</w>
<w >saa</w>
<w >sanctam</w>
<w >petronillam</w>
<w >wara</w>
<w >framlidhna</w>
<w >,</w>
<w >mz</w>
<w >dödhen</w>
<w >,</w>
<w >wändhe</w>
<w >han</w>
<w >sin</w>
<w >hogh</w>
<w >oc</w>
<w >hiärta</w>
<w >til</w>
<w >enna</w>
<w >wälsläktadha</w>
<w >,</w>
<w >oc</w>
<w >wänasta</w>
<w >iomffru</w>
<w >,</w>
<w >som</w>
<w >kalladhes</w>
<w >felicula</w>
<w >,</w>
<w >Tässen</w>
<w >iomffrun</w>
<w >war</w>
<w >cristen</w>
<w >oc</w>
<w >gudelik</w>
<w >människia</w>
<w >,</w>
<w >til</w>
<w >hänna</w>
<w >taladhe</w>
<w >flacchus</w>
<w >greffwe</w>
<w >sighiandes</w>
<w >,</w>
<w >tw</w>
<w >wilkor</w>
<w >lägher</w>
<w >iak</w>
<w >tik</w>
<w >före</w>
<w >,</w>
<w >wt</w>
<w >wäl</w>
<w >huilket</w>
<w >tik</w>
<w >täkkes</w>
<w >,</w>
<w >Antiggia</w>
<w >at</w>
<w >thu</w>
<w >bliff</w>
<w >min</w>
<w >hwstru</w>
<w >ällar</w>
<w >offra</w>
<w >warom</w>
<w >gudhom</w>
<w >¶</w>
<w >Sancta</w>
<w >felicula</w>
<w >swaradhe</w>
<w >,</w>
<w >thin</w>
<w >hwstru</w>
<w >wardher</w>
<w >iak</w>
<w >aldrig</w>
<w >thy</w>
<w >iak</w>
<w >är</w>
<w >ihesu</w>
<w >cristo</w>
<w >til</w>
<w >wigdh</w>
<w >,</w>
<w >ey</w>
<w >häldher</w>
<w >skal</w>
<w >iak</w>
<w >gudhomen</w>
<w >offra</w>
<w >,</w>
<w >thy</w>
<w >at</w>
<w >iak</w>
<w >är</w>
<w >cristen</w>
<w >människia</w>
<w >,</w>
<w >tha</w>
<w >grepp</w>
<w >flacchus</w>
<w >hälga</w>
<w >iomffruna</w>
<w >,</w>
<w >antwardandhe</w>
<w >hänne</w>
<w >sinom</w>
<w >wndhe</w>
<w >greffua</w>
<w >,</w>
<w >oc</w>
<w >läth</w>
<w >hänne</w>
<w >jnnelykkias</w>
<w >i</w>
<w >mörko</w>
<w >hwse</w>
<w >,</w>
<w >wtan</w>
<w >alla</w>
<w >födho</w>
<w >,</w>
<w >ällar</w>
<w >math</w>
<w >i</w>
<w >vij</w>
<w >dynghn</w>
<w >i</w>
<w >hwilken</w>
<w >vij</w>
<w >dynghn</w>
<w >,</w>
<w >gömarannas</w>
<w >hustrur</w>
<w >gingho</w>
<w >idkelika</w>
<w >til</w>
<w >iomffrunna</w>
<w >,</w>
<w >sighiandis</w>
<w >til</w>
<w >hänna</w>
<w >,</w>
<w >O</w>
<w >aldra</w>
<w >kärasta</w>
<w >oc</w>
<w >wänasta</w>
<w >iomffru</w>
<w >hwi</w>
<w >wtsäl</w>
<w >thu</w>
<w >swa</w>
<w >smälekan</w>
<w >,</w>
<w >oc</w>
<w >wärsta</w>
<w >dödh</w>
<w >,</w>
<w >tak</w>
<w >häldher</w>
<w >wälbornan</w>
<w >man</w>
<w >rikan</w>
<w >oc</w>
<w >mäktoghan</w>
<w >greffua</w>
<w >,</w>
<w >tik</w>
<w >til</w>
<w >brudhgomma</w>
<w >oc</w>
<w >bondha</w>
<w >,</w>
<w >han</w>
<w >är</w>
<w >wngher</w>
<w >oc</w>
<w >karsker</w>
<w >oc</w>
<w >kesarens</w>
<w >wen</w>
<w >Sancta</w>
<w >felicula</w>
<w >thzta</w>
<w >hörandes</w>
<w >,</w>
<w >gaff</w>
<w >them</w>
<w >enghen</w>
<w >annor</w>
<w >swar</w>
<w >,</w>
<w >wtan</w>
<w >sagdhe</w>
<w >Jak</w>
<w >är</w>
<w >cristi</w>
<w >iomffru</w>
<w >,</w>
<w >oc</w>
<w >enghen</w>
<w >annan</w>
<w >skal</w>
<w >iak</w>
<w >taka</w>
<w >mik</w>
<w >til</w>
<w >brudhgomma</w>
<w >,</w>
<w >tha</w>
<w >wart</w>
<w >sancta</w>
<w >felicula</w>
<w >fran</w>
<w >them</w>
<w >wt</w>
<w >skwten</w>
<w >mz</w>
<w >smälekhet</w>
<w >oc</w>
<w >ledhes</w>
<w >,</w>
<w >til</w>
<w >greffwans</w>
<w >iomffrwr</w>
<w >huilka</w>
<w >han</w>
<w >flere</w>
<w >haffde</w>
<w >,</w>
<w >oc</w>
<w >bleff</w>
<w >mz</w>
</sentence>
</paragraph>
<paragraph n="5">
<sentence n="5" id="59b797a-59b5bdc">
<w >I</w>
<w >:</w>
<w >334</w>
<w >them</w>
<w >i</w>
<w >syw</w>
<w >dagha</w>
<w >,</w>
<w >wtan</w>
<w >maat</w>
<w >oc</w>
<w >alzskona</w>
<w >födho</w>
<w >,</w>
<w >thy</w>
<w >at</w>
<w >the</w>
<w >kwnno</w>
<w >ey</w>
<w >i</w>
<w >nakre</w>
<w >matto</w>
<w >komma</w>
<w >hänne</w>
<w >til</w>
<w >at</w>
<w >taka</w>
<w >mat</w>
<w >ällar</w>
<w >nakra</w>
<w >födho</w>
<w >aff</w>
<w >theras</w>
<w >handom</w>
<w >Tha</w>
<w >greffuen</w>
<w >thz</w>
<w >hördhe</w>
<w >,</w>
<w >läth</w>
<w >han</w>
<w >stwpogreffwana</w>
<w >,</w>
<w >opp</w>
<w >hänghia</w>
<w >hälgha</w>
<w >iomffrwna</w>
<w >,</w>
<w >opp</w>
<w >fran</w>
<w >iordhenne</w>
<w >mz</w>
<w >armana</w>
<w >i</w>
<w >wädhret</w>
<w >jn</w>
<w >eculeno</w>
<w >,</w>
<w >thz</w>
<w >är</w>
<w >som</w>
<w >en</w>
<w >lagher</w>
<w >galghe</w>
<w >,</w>
<w >i</w>
<w >huilkom</w>
<w >hedningane</w>
<w >pläghado</w>
<w >pina</w>
<w >hälga</w>
<w >martires</w>
<w >,</w>
<w >them</w>
<w >thär</w>
<w >opphängiandis</w>
<w >stwndhom</w>
<w >mz</w>
<w >hareth</w>
<w >,</w>
<w >stwndom</w>
<w >mz</w>
<w >armom</w>
<w >stwndom</w>
<w >mz</w>
<w >föthrena</w>
<w >,</w>
<w >än</w>
<w >tha</w>
<w >sancta</w>
<w >felicula</w>
<w >war</w>
<w >swa</w>
<w >opphängd</w>
<w >,</w>
<w >tha</w>
<w >ropadhe</w>
<w >hon</w>
<w >mz</w>
<w >höghe</w>
<w >röst</w>
<w >sighiandis</w>
<w >,</w>
<w >¶</w>
<w >Nw</w>
<w >begynnadhe</w>
<w >iak</w>
<w >skodha</w>
<w >min</w>
<w >älskara</w>
<w >ihesum</w>
<w >cristum</w>
<w >,</w>
<w >i</w>
<w >huilkom</w>
<w >min</w>
<w >älskoghe</w>
<w >är</w>
<w >fäster</w>
<w >,</w>
<w >Tha</w>
<w >taladhe</w>
<w >aldher</w>
<w >näst</w>
<w >standande</w>
<w >almoghen</w>
<w >til</w>
<w >hänna</w>
<w >,</w>
<w >oc</w>
<w >iämwäl</w>
<w >stwpogreffwane</w>
<w >huilke</w>
<w >pinadho</w>
<w >hänne</w>
<w >sighiandis</w>
<w >O</w>
<w >felicula</w>
<w >wänasta</w>
<w >iomffru</w>
<w >tänk</w>
<w >thina</w>
<w >ädhlahet</w>
<w >,</w>
<w >oc</w>
<w >neka</w>
<w >at</w>
<w >thu</w>
<w >äst</w>
<w >cristen</w>
<w >människia</w>
<w >,</w>
<w >tha</w>
<w >math</w>
<w >thu</w>
<w >wardha</w>
<w >lös</w>
<w >oc</w>
<w >qwit</w>
<w >,</w>
<w >aff</w>
<w >tässe</w>
<w >grymme</w>
<w >pino</w>
<w >som</w>
<w >tik</w>
<w >bidhar</w>
<w >,</w>
<w >Tha</w>
<w >ropadhe</w>
<w >sancta</w>
<w >felicula</w>
<w >mz</w>
<w >glädhe</w>
<w >röst</w>
<w >sighiandis</w>
<w >Jak</w>
<w >skal</w>
<w >ey</w>
<w >neka</w>
<w >min</w>
<w >älskara</w>
<w >,</w>
<w >huilken</w>
<w >för</w>
<w >mina</w>
<w >skuldh</w>
<w >,</w>
<w >wart</w>
<w >mathadher</w>
<w >mz</w>
<w >galla</w>
<w >,</w>
<w >skänkther</w>
<w >mz</w>
<w >äthikio</w>
<w >,</w>
<w >kronadher</w>
<w >mz</w>
<w >torn</w>
<w >oc</w>
<w >korsfäster</w>
<w >mz</w>
<w >spikom</w>
<w >¶</w>
<w >Nar</w>
<w >hälga</w>
<w >iomffrun</w>
<w >war</w>
<w >nw</w>
<w >langha</w>
<w >pinadh</w>
<w >mz</w>
<w >hugh</w>
<w >oc</w>
<w >flänghiom</w>
<w >,</w>
<w >oc</w>
<w >wille</w>
<w >engaledhes</w>
<w >neka</w>
<w >cristum</w>
<w >,</w>
<w >toko</w>
<w >the</w>
<w >hänne</w>
<w >nidher</w>
<w >halffdödha</w>
<w >,</w>
<w >oc</w>
<w >hänne</w>
<w >til</w>
<w >större</w>
<w >smälikhet</w>
<w >kastadho</w>
<w >the</w>
<w >hänna</w>
<w >likama</w>
<w >nidher</w>
<w >i</w>
<w >eth</w>
<w >orenasta</w>
<w >priweth</w>
<w >,</w>
<w >oc</w>
<w >ther</w>
<w >bleff</w>
<w >hon</w>
<w >dödh</w>
<w >,</w>
<w >aff</w>
<w >wärste</w>
<w >lukt</w>
<w >,</w>
<w >oc</w>
<w >siälen</w>
<w >anamadhes</w>
<w >oc</w>
<w >oppfördhes</w>
<w >i</w>
<w >hymmelen</w>
<w >,</w>
<w >mz</w>
<w >otalekom</w>
<w >änglaskara</w>
<w >,</w>
<w >hwar</w>
<w >hon</w>
<w >nw</w>
<w >fröghdas</w>
<w >oc</w>
<w >glädz</w>
<w >mz</w>
<w >sin</w>
<w >söta</w>
<w >älskara</w>
<w >ihesu</w>
<w >cristo</w>
<w >¶</w>
<w >Än</w>
<w >nichomedus</w>
<w >prester</w>
<w >,</w>
<w >nar</w>
<w >han</w>
<w >hördhe</w>
<w >hwat</w>
<w >giorth</w>
<w >war</w>
<w >mz</w>
<w >sancta</w>
<w >felicula</w>
<w >,</w>
<w >tok</w>
<w >han</w>
<w >om</w>
<w >nattatidh</w>
<w >hännas</w>
</sentence>
</paragraph>
<paragraph n="6">
<sentence n="6" id="59b5bdc-59b0179">
<w >I</w>
<w >:</w>
<w >335</w>
<w >likama</w>
<w >opp</w>
<w >aff</w>
<w >orenasta</w>
<w >priuethet</w>
<w >oc</w>
<w >twättadhe</w>
<w >han</w>
<w >oc</w>
<w >fördhe</w>
<w >han</w>
<w >liket</w>
<w >vij</w>
<w >walzska</w>
<w >milor</w>
<w >fran</w>
<w >romara</w>
<w >stadh</w>
<w >lönlika</w>
<w >,</w>
<w >i</w>
<w >them</w>
<w >wäghenom</w>
<w >som</w>
<w >kallas</w>
<w >ardiatina</w>
<w >,</w>
<w >til</w>
<w >en</w>
<w >aker</w>
<w >,</w>
<w >ällar</w>
<w >iordha</w>
<w >mon</w>
<w >,</w>
<w >som</w>
<w >sanctus</w>
<w >nichomedus</w>
<w >war</w>
<w >siälffuer</w>
<w >äghandis</w>
<w >,</w>
<w >oc</w>
<w >ther</w>
<w >iordhadhe</w>
<w >han</w>
<w >sanctam</w>
<w >feliculam</w>
<w >mz</w>
<w >störste</w>
<w >wördhnigh</w>
<w >oc</w>
<w >gudelikhet</w>
<w >,</w>
<w >oc</w>
<w >göras</w>
<w >thär</w>
<w >iärtekn</w>
<w >,</w>
<w >oc</w>
<w >manghe</w>
<w >nywta</w>
<w >hännas</w>
<w >böner</w>
<w >aat</w>
<w >oc</w>
<w >wnfaa</w>
<w >sina</w>
<w >hälso</w>
<w >för</w>
<w >hännas</w>
<w >häloghetz</w>
<w >skuldh</w>
<w >än</w>
<w >til</w>
<w >thänna</w>
<w >när</w>
<w >warandhes</w>
<w >dagh</w>
<w >Tha</w>
<w >flaccus</w>
<w >greffwe</w>
<w >bespordhe</w>
<w >,</w>
<w >at</w>
<w >sanctus</w>
<w >nicomedus</w>
<w >haffde</w>
<w >swa</w>
<w >wördhelika</w>
<w >begangit</w>
<w >hälga</w>
<w >iomffrwna</w>
<w >,</w>
<w >tha</w>
<w >läth</w>
<w >han</w>
<w >gripa</w>
<w >honom</w>
<w >,</w>
<w >oc</w>
<w >ledhas</w>
<w >til</w>
<w >affgudha</w>
<w >mönstrit</w>
<w >,</w>
<w >The</w>
<w >som</w>
<w >han</w>
<w >leddo</w>
<w >sagdho</w>
<w >til</w>
<w >honom</w>
<w >Thu</w>
<w >skalt</w>
<w >til</w>
<w >bidhia</w>
<w >oc</w>
<w >ära</w>
<w >wara</w>
<w >gudha</w>
<w >Sanctus</w>
<w >nicomedus</w>
<w >swaradhe</w>
<w >,</w>
<w >Jak</w>
<w >tilbidher</w>
<w >enghen</w>
<w >gudh</w>
<w >,</w>
<w >ällar</w>
<w >nakrom</w>
<w >gudh</w>
<w >,</w>
<w >gör</w>
<w >mith</w>
<w >offer</w>
<w >,</w>
<w >wtan</w>
<w >herranom</w>
<w >ihesu</w>
<w >cristo</w>
<w >alzmäktoghom</w>
<w >som</w>
<w >styrer</w>
<w >i</w>
<w >hymerike</w>
<w >äwerdelika</w>
<w >,</w>
<w >än</w>
<w >tässom</w>
<w >gudhomen</w>
<w >,</w>
<w >som</w>
<w >här</w>
<w >staa</w>
<w >jnnelykte</w>
<w >i</w>
<w >mönstrit</w>
<w >,</w>
<w >som</w>
<w >the</w>
<w >bwndhne</w>
<w >waro</w>
<w >,</w>
<w >i</w>
<w >nakot</w>
<w >fangha</w>
<w >hws</w>
<w >,</w>
<w >offrar</w>
<w >iak</w>
<w >aldrig</w>
<w >¶</w>
<w >Nar</w>
<w >sanctus</w>
<w >nicomedus</w>
<w >haffde</w>
<w >talat</w>
<w >tässe</w>
<w >ordh</w>
<w >,</w>
<w >oc</w>
<w >mangh</w>
<w >annor</w>
<w >,</w>
<w >straffandhes</w>
<w >aff</w>
<w >gudha</w>
<w >dyrkan</w>
<w >,</w>
<w >lät</w>
<w >domaren</w>
<w >honom</w>
<w >hardelika</w>
<w >slaas</w>
<w >mz</w>
<w >blystöptom</w>
<w >käppom</w>
<w >,</w>
<w >til</w>
<w >thäs</w>
<w >han</w>
<w >gaff</w>
<w >opp</w>
<w >sina</w>
<w >siäl</w>
<w >,</w>
<w >i</w>
<w >hälgas</w>
<w >änglas</w>
<w >händher</w>
<w >,</w>
<w >än</w>
<w >kroppen</w>
<w >dödhan</w>
<w >,</w>
<w >lät</w>
<w >han</w>
<w >kasta</w>
<w >i</w>
<w >flodhena</w>
<w >thyrim</w>
<w >,</w>
<w >huilket</w>
<w >en</w>
<w >cristen</w>
<w >präster</w>
<w >saa</w>
<w >,</w>
<w >han</w>
<w >kalladhes</w>
<w >iustus</w>
<w >,</w>
<w >oc</w>
<w >om</w>
<w >nattatidh</w>
<w >,</w>
<w >sökte</w>
<w >han</w>
<w >kroppen</w>
<w >opp</w>
<w >,</w>
<w >i</w>
<w >flodhenne</w>
<w >,</w>
<w >oc</w>
<w >fördhe</w>
<w >til</w>
<w >sin</w>
<w >yrthagardh</w>
<w >som</w>
<w >han</w>
<w >äghandes</w>
<w >war</w>
<w >,</w>
<w >wtan</w>
<w >widh</w>
<w >stadz</w>
<w >mwren</w>
<w >i</w>
<w >wäghenom</w>
<w >som</w>
<w >kallas</w>
<w >nwmentana</w>
<w >,</w>
<w >oc</w>
<w >thär</w>
<w >iordadhe</w>
<w >han</w>
<w >sanctum</w>
<w >nicomedem</w>
<w >,</w>
<w >wördhelika</w>
<w >,</w>
<w >i</w>
<w >huilkom</w>
<w >stadh</w>
<w >,</w>
<w >alle</w>
<w >nödhstadde</w>
<w >,</w>
<w >wnfa</w>
<w >hiälp</w>
<w >oc</w>
<w >lisaa</w>
<w >,</w>
<w >aff</w>
<w >sinne</w>
<w >nödh</w>
<w >för</w>
</sentence>
</paragraph>
<paragraph n="7">
<sentence n="7" id="59b0179-59b7f53">
<w >I</w>
<w >:</w>
<w >336</w>
<w >sancti</w>
<w >nicomedis</w>
<w >martyris</w>
<w >bön</w>
<w >oc</w>
<w >förskullan</w>
<w >,</w>
<w >huilken</w>
<w >pino</w>
<w >oc</w>
<w >dödh</w>
<w >ledh</w>
<w >för</w>
<w >ihesu</w>
<w >cristi</w>
<w >tro</w>
<w >oc</w>
<w >kärlek</w>
<w >skuld</w>
<w >,</w>
<w >honom</w>
<w >wari</w>
<w >loff</w>
<w >oc</w>
<w >ära</w>
<w >aff</w>
<w >all</w>
<w >creatur</w>
<w >äwerdhelika</w>
<w >,</w>
<w >Sancta</w>
<w >felicula</w>
<w >dagher</w>
<w >,</w>
<w >är</w>
<w >tridhia</w>
<w >daghen</w>
<w >näst</w>
<w >äpther</w>
<w >sancti</w>
<w >barnabe</w>
<w >apostoli</w>
<w >dagh</w>
<w >,</w>
<w >thz</w>
<w >är</w>
<w >xiij</w>
<w >daghen</w>
<w >junni</w>
<w >manadh</w>
</sentence>
</paragraph>
</text>
</corpus>
